tomlev/__init__.py
tomlev/__main__.py
tomlev/__model__.py
tomlev/cli.py
tomlev/constants.py
tomlev/converters.py
tomlev/env_loader.py
tomlev/errors.py
tomlev/include_handler.py
tomlev/parser.py
tomlev/patterns.py
tomlev/py.typed
tomlev-1.0.7.dist-info/METADATA
tomlev-1.0.7.dist-info/WHEEL
tomlev-1.0.7.dist-info/entry_points.txt
tomlev-1.0.7.dist-info/licenses/LICENSE
tomlev-1.0.7.dist-info/RECORD
