Metadata-Version: 2.4
Name: tomlev
Version: 1.0.7
Summary: Type-safe TOML configuration management with environment variable substitution and automatic validation for modern Python applications.
Project-URL: Homepage, https://github.com/thesimj/tomlev
Project-URL: Repository, https://github.com/thesimj/tomlev
Project-URL: Bug Tracker, https://github.com/thesimj/tomlev/issues
Project-URL: Documentation, https://github.com/thesimj/tomlev/blob/main/README.md
Project-URL: Changelog, https://github.com/thesimj/tomlev/blob/main/CHANGELOG.md
Project-URL: Discussions, https://github.com/thesimj/tomlev/discussions
Project-URL: Funding, https://github.com/sponsors/thesimj
Project-URL: Security, https://github.com/thesimj/tomlev/security
Author-email: Nick Bubelich <m+github@bubelich.com>
License: MIT
License-File: LICENSE
Keywords: 12-factor,app-config,config-management,configuration,dotenv,env,env-substitution,environment-variables,pydantic-like,python-config,schema,settings,toml,type-hints,type-safety,typed,validation
Classifier: Development Status :: 5 - Production/Stable
Classifier: Environment :: Console
Classifier: Intended Audience :: Developers
Classifier: Intended Audience :: Information Technology
Classifier: Intended Audience :: System Administrators
Classifier: License :: OSI Approved :: MIT License
Classifier: Operating System :: MacOS
Classifier: Operating System :: Microsoft :: Windows
Classifier: Operating System :: OS Independent
Classifier: Operating System :: POSIX :: Linux
Classifier: Programming Language :: Python :: 3 :: Only
Classifier: Programming Language :: Python :: 3.11
Classifier: Programming Language :: Python :: 3.12
Classifier: Programming Language :: Python :: 3.13
Classifier: Programming Language :: Python :: 3.14
Classifier: Programming Language :: Python :: Implementation :: CPython
Classifier: Programming Language :: Python :: Implementation :: PyPy
Classifier: Topic :: Software Development
Classifier: Topic :: Software Development :: Libraries :: Python Modules
Classifier: Topic :: System :: Installation/Setup
Classifier: Topic :: System :: Systems Administration
Classifier: Topic :: Utilities
Classifier: Typing :: Typed
Requires-Python: >=3.11
